[
  {
    "jmeno": "Tomas",
    "prijmeni": "Novotný",
    "uzJmeno": "tomasos1",
    "id": 3,
    "pozice": "Boss",
    "telefon": "792",
    "mail": "aa@se.cz",
    "heslo": "1234"
  },
  {
    "jmeno": "Adam",
    "prijmeni": "Rychlý",
    "uzJmeno": "adam12",
    "id": 4,
    "pozice": "Cisnik",
    "telefon": "792",
    "mail": "aa@se.cz",
    "heslo": "1234"
  },
  {
    "jmeno": "Vojta",
    "prijmeni": "Dvořák",
    "uzJmeno": "vojtik22",
    "id": 2,
    "pozice": "Kuchar",
    "telefon": "792",
    "mail": "aa@se.cz",
    "heslo": "1234"
  },
  {
    "jmeno": "Karel",
    "prijmeni": "Novák",
    "uzJmeno": "karlos1",
    "id": 1,
    "pozice": "Kuchar",
    "telefon": "792",
    "mail": "aa@se.cz",
    "heslo": "1234"
  },
  {
    "jmeno": "adam",
    "prijmeni": "michal",
    "uzJmeno": "mika",
    "id": 5,
    "pozice": "Manager",
    "telefon": "9283",
    "mail": "maaij@s.cz",
    "heslo": "heslo"
  },
  {
    "jmeno": "Karel",
    "prijmeni": "Adam",
    "uzJmeno": "karl111",
    "id": 6,
    "pozice": "Manager",
    "telefon": "123",
    "mail": "123",
    "heslo": "123"
  },
  {
    "jmeno": "Karel",
    "prijmeni": "Karlik",
    "uzJmeno": "karel1234",
    "id": 7,
    "pozice": "Manager",
    "telefon": "788287888",
    "mail": "m.c@mail.cz",
    "heslo": "ahoj"
  }
]